{
  "data": {
    "id": 61365484,
    "btag": "Beast",
    "name": "Beast",
    "guildId": null,
    "guildName": null,
    "avatar": "Indicator_DarkmoonFaire_Eyes",
    "skulls": 122,
    "level": 38,
    "pvpWins": 286,
    "leaderA": "BaronRivendareLeader",
    "leaderAWins": 48,
    "leaderAHonor": 3046,
    "leaderB": "ThaurissanLeader",
    "leaderBWins": 32,
    "leaderBHonor": 3434,
    "leaderC": "TirionLeader",
    "leaderCWins": 68,
    "leaderCHonor": 3272,
    "socials": null,
    "armies": [
      [
        "JainaLeader;;15",
        "S.A.F.E.PilotFlyingMachine;CominInHot;17",
        "Huntress;ElvenMight;17",
        "Blizzard;ColdSnap;20",
        "Harpy;InfectiousSwipes;19",
        "OgreMage;FrostfireBolt;18",
        "GoblinSapper;RocketBoots;20"
      ],
      [
        "TirionLeader;DivineShield;20",
        "Blizzard;ColdSnap;20",
        "GryphonRider;MightyThrow;20",
        "Gargoyle;WingBuffet;21",
        "Chimaera;Leviathan;20",
        "CoreHounds;FieryRebirth;20",
        "Shaman;LightningMastery;20"
      ],
      [
        "OldMurkEyeLeader;TipOfTheSpear;20",
        "Harpy;InfectiousSwipes;19",
        "Prowler;OnTheProwl;18",
        "FireElemental;ImmolationAura;19",
        "Pyromancer;BlazeOfGlory;20",
        "Chimaera;Leviathan;20",
        "Blizzard;ColdSnap;20"
      ],
      [
        "GrommashLeader;SavageStrikes;17",
        "StonehoofTauren;Provoke;19",
        "PlagueFarmer;SplashingPumpkins;16",
        "DefiasBandits;;14",
        "S.A.F.E.PilotFlyingMachine;CominInHot;17",
        "Pyromancer;BlazeOfGlory;18",
        "Prowler;OnTheProwl;18"
      ],
      [
        "RendLeader;FlamingSoul;20",
        "WhelpEggs;FlameBurst;18",
        "FireElemental;ImmolationAura;19",
        "Drake;EngulfingFlames;20",
        "Blizzard;BrittleIce;20",
        "Gargoyle;WingBuffet;21",
        "Harpy;InfectiousSwipes;19"
      ],
      [
        "BloodmageThalnosLeader;;14",
        "Abomination;NoxiousPresence;20",
        "PlagueFarmer;SplashingPumpkins;17",
        "S.A.F.E.PilotFlyingMachine;CominInHot;17",
        "Prowler;OnTheProwl;18",
        "Pyromancer;BlazeOfGlory;18",
        "DefiasBandits;;16"
      ],
      [
        "MaievLeader;;16",
        "Footmen;ShieldBash;20",
        "S.A.F.E.PilotFlyingMachine;CominInHot;17",
        "Worgen;LoneWolf;17",
        "Gargoyle;WingBuffet;21",
        "WhelpEggs;FlameBurst;18",
        "Quilboar;BrambleBurst;18"
      ],
      [
        "HoggerLeader;HamHock;19",
        "Quilboar;BrambleBurst;18",
        "Chimaera;Leviathan;20",
        "GryphonRider;OdynsFury;20",
        "Harpy;InfectiousSwipes;19",
        "GoblinSapper;RocketBoots;20",
        "Execute;Bloodthirsty;18"
      ],
      [
        "CairneLeader;Reincarnation;23",
        "DarkspearTroll;BigBadVoodoo;21",
        "WarsongRaider;RazingFocus;18",
        "Pyromancer;BlazeOfGlory;20",
        "Quilboar;BrambleBurst;18",
        "Blizzard;ColdSnap;20",
        "Chimaera;Leviathan;20"
      ],
      [
        "BaronRivendareLeader;ChillOfTheGrave;20",
        "Abomination;NoxiousPresence;20",
        "PlagueFarmer;SplashingPumpkins;19",
        "BatRider;FlamingPitch;18",
        "Gargoyle;WingBuffet;21",
        "Harpy;InfectiousSwipes;19",
        "WhelpEggs;FlameBurst;18"
      ],
      [
        "SneedLeader;;10",
        "StonehoofTauren;Provoke;12",
        "DarkspearTroll;;11",
        "GoblinSapper;;10",
        "WarsongRaider;;10",
        "Blizzard;BrittleIce;12",
        "Shaman;;10"
      ],
      [
        "DrakkisathLeader;;10",
        "FireElemental;ImmolationAura;17",
        "CoreHounds;FieryRebirth;19",
        "Blizzard;BrittleIce;17",
        "Gargoyle;WingBuffet;18",
        "Quilboar;BrambleBurst;17",
        "DarkspearTroll;Headhunting;19"
      ],
      [
        "ThaurissanLeader;MoirasWit;20",
        "Pyromancer;BlazeOfGlory;20",
        "CoreHounds;FieryRebirth;20",
        "DefiasBandits;PickLock;19",
        "FireElemental;ImmolationAura;19",
        "PlagueFarmer;SplashingPumpkins;19",
        "DarkspearTroll;BigBadVoodoo;21"
      ],
      [
        "SylvanasLeader;BlackArrow;20",
        "Abomination;NoxiousPresence;20",
        "Gargoyle;WingBuffet;21",
        "Shaman;LightningMastery;20",
        "GoblinSapper;RocketBoots;20",
        "Execute;Bloodthirsty;18",
        "Harpy;InfectiousSwipes;19"
      ]
    ],
    "lastUpdate": 1719193319
  },
  "token": "4241b2fa-e80a-48b4-a1a6-afeb8f25c9ed"
}